setup.py
plmap/__init__.py
plmap/plmapp.py
plmap/plmapt.py
plmap/progress_bar.py
plmap.egg-info/PKG-INFO
plmap.egg-info/SOURCES.txt
plmap.egg-info/dependency_links.txt
plmap.egg-info/top_level.txt