Metadata-Version: 1.0
Name: plmap
Version: 2.0.0
Summary: Parallel map using multi-threading and multi-processing
Home-page: https://github.com/brlohith/parallelization
Author: Lohith B R
Author-email: UNKNOWN
License: MIT
Keywords: parallelization plmap plmapp plmapt pmapp multi-threading multi-processing parallel map
Platform: UNKNOWN
